contentstack_management/__init__.py
contentstack_management/_api_client.py
contentstack_management/_constant.py
contentstack_management/_errors.py
contentstack_management/common.py
contentstack_management/contentstack.py
contentstack_management/aliases/__init__.py
contentstack_management/aliases/aliases.py
contentstack_management/assets/__init__.py
contentstack_management/assets/assets.py
contentstack_management/auditlogs/__init__.py
contentstack_management/auditlogs/auditlog.py
contentstack_management/branches/__init__.py
contentstack_management/branches/branches.py
contentstack_management/bulk_operations/__init__.py
contentstack_management/bulk_operations/bulk_operation.py
contentstack_management/content_types/__init__.py
contentstack_management/content_types/content_type.py
contentstack_management/delivery_token/__init__.py
contentstack_management/delivery_token/delivery_token.py
contentstack_management/entries/__init__.py
contentstack_management/entries/entry.py
contentstack_management/entry_variants/__init__.py
contentstack_management/entry_variants/entry_variants.py
contentstack_management/environments/__init__.py
contentstack_management/environments/environment.py
contentstack_management/extensions/__init__.py
contentstack_management/extensions/extension.py
contentstack_management/global_fields/__init__.py
contentstack_management/global_fields/global_fields.py
contentstack_management/labels/__init__.py
contentstack_management/labels/label.py
contentstack_management/locale/__init__.py
contentstack_management/locale/locale.py
contentstack_management/management_token/__init__.py
contentstack_management/management_token/management_token.py
contentstack_management/metadata/__init__.py
contentstack_management/metadata/metadata.py
contentstack_management/oauth/__init__.py
contentstack_management/oauth/oauth_handler.py
contentstack_management/oauth/oauth_interceptor.py
contentstack_management/organizations/__init__.py
contentstack_management-1.7.0.dist-info/licenses/LICENSE
contentstack_management-1.7.0.dist-info/METADATA
contentstack_management-1.7.0.dist-info/WHEEL
contentstack_management-1.7.0.dist-info/top_level.txt
contentstack_management-1.7.0.dist-info/RECORD
