Metadata-Version: 2.4
Name: contentstack-management
Version: 1.7.0
Summary: Contentstack API Client Library for Python
Home-page: https://github.com/contentstack/contentstack-management-python
Author: dev-ex
Author-email: mobile@contentstack.com
License: MIT
Classifier: License :: OSI Approved :: MIT License
Classifier: Programming Language :: Python :: 3.10
Classifier: Operating System :: OS Independent
Requires-Python: >=3.9
License-File: LICENSE
Requires-Dist: bson>=0.5.9
Requires-Dist: requests>=2.5.4
Requires-Dist: requests-toolbelt>=0.3.1
Provides-Extra: dev
Requires-Dist: pytest>=7.0; extra == "dev"
Requires-Dist: twine>=4.0.2; extra == "dev"
Requires-Dist: dotenv>=0.0.5; extra == "dev"
Dynamic: author
Dynamic: author-email
Dynamic: classifier
Dynamic: description
Dynamic: description-content-type
Dynamic: home-page
Dynamic: license
Dynamic: license-file
Dynamic: provides-extra
Dynamic: requires-dist
Dynamic: requires-python
Dynamic: summary
